LICENSE
MANIFEST.in
README.md
setup.cfg
setup.py
djangocms_responsive_image/__init__.py
djangocms_responsive_image/admin.py
djangocms_responsive_image/cms_plugins.py
djangocms_responsive_image/conf.py
djangocms_responsive_image/forms.py
djangocms_responsive_image/models.py
djangocms_responsive_image/utils.py
djangocms_responsive_image/views.py
djangocms_responsive_image.egg-info/PKG-INFO
djangocms_responsive_image.egg-info/SOURCES.txt
djangocms_responsive_image.egg-info/dependency_links.txt
djangocms_responsive_image.egg-info/requires.txt
djangocms_responsive_image.egg-info/top_level.txt
djangocms_responsive_image/migrations/0001_initial.py
djangocms_responsive_image/migrations/0002_auto_20160128_1540.py
djangocms_responsive_image/migrations/__init__.py
djangocms_responsive_image/templates/djangocms_responsive_image/plugins/image/default.html
djangocms_responsive_image/templates/djangocms_responsive_image/snippets/image.html
djangocms_responsive_image/templatetags/__init__.py
djangocms_responsive_image/templatetags/responsive_image.py