Metadata-Version: 1.1
Name: djangocms-responsive-image
Version: 0.2
Summary: Django CMS plugin implementing html5 responsive images
Home-page: https://github.com/febsn/djangocms-responsive-image
Author: Fabian Lehner
Author-email: fl@makonis.net
License: MIT License
Download-URL: https://github.com/febsn/djangocms-responsive-image/tarball/0.2
Keywords: responsive,image,django
Platform: UNKNOWN
